laiiqa/__init__.py
laiiqa/helpers.py
laiiqa/ozonation.py
laiiqa/raw.py
laiiqa/spectrouv.py
laiiqa_lab_utilities-0.1.0.dist-info/LICENSE
laiiqa_lab_utilities-0.1.0.dist-info/METADATA
laiiqa_lab_utilities-0.1.0.dist-info/WHEEL
laiiqa_lab_utilities-0.1.0.dist-info/top_level.txt
laiiqa_lab_utilities-0.1.0.dist-info/RECORD
