Metadata-Version: 2.1
Name: laiiqa-lab-utilities
Version: 0.1.0
Summary: Package for ozonation, spectro uv and bioreaction data analysis files for the LAIIQA laboratory (ESIQIE - IPN).
Home-page: UNKNOWN
Author: F. Javier Morales M.
Author-email: fmoralesm87@gmail.com
License: MIT License
Platform: UNKNOWN
Classifier: Development Status :: 2 - Pre-Alpha
Classifier: License :: OSI Approved :: MIT License
Classifier: Programming Language :: Python :: 3.0
Classifier: Programming Language :: Python :: 3.6
Classifier: Programming Language :: Python :: 3.7
Classifier: Operating System :: OS Independent
Classifier: Operating System :: Microsoft :: Windows
Classifier: Operating System :: MacOS
Classifier: Operating System :: POSIX :: Linux
Classifier: Topic :: Scientific/Engineering
Classifier: Intended Audience :: Science/Research
Classifier: Intended Audience :: Developers
Classifier: Intended Audience :: Education
Requires-Python: >=3.7
License-File: LICENSE
Requires-Dist: natsort
Requires-Dist: numpy
Requires-Dist: pandas
Requires-Dist: matplotlib
Requires-Dist: h5py
Requires-Dist: sklearn
Requires-Dist: IPython
